backbonetools/__init__.py
backbonetools/exec.py
backbonetools/io/__init__.py
backbonetools/io/inputs.py
backbonetools/io/investInit_template.gms
backbonetools/io/outputs.py
backbonetools-2025.0.3.dist-info/METADATA
backbonetools-2025.0.3.dist-info/WHEEL
backbonetools-2025.0.3.dist-info/licenses/LICENSE
backbonetools-2025.0.3.dist-info/RECORD
