Metadata-Version: 2.4
Name: BackboneTools
Version: 2025.0.3
Summary: BackboneTools is a Python package for working with Backbone.
Project-URL: Repository, https://gitlab.ruhr-uni-bochum.de/ee/backbonetools.git
Author-email: David Huckebrink <david.huckebrink@rub.de>, Leonie Plaga <leonie.plaga@rub.de>
License-File: LICENSE
Requires-Dist: gamsapi
Requires-Dist: matplotlib
Requires-Dist: nbformat
Requires-Dist: numpy
Requires-Dist: openpyxl
Requires-Dist: pandas
Requires-Dist: plotly
Requires-Dist: pytest
Requires-Dist: tsam
